[
  {
    "topology": "Abilene",
    "nodes": 11,
    "edges": 14,
    "density": 0.2545454545454545,
    "sp_lpp_mean": 7.4362,
    "sp_lpp_std": 1.2502140291248895,
    "sp_loss_mean": 56.3,
    "sp_loss_std": 17.10242975276542,
    "em_lpp_mean": 8.51606,
    "em_lpp_std": 1.404215425952428,
    "em_loss_mean": 22.6,
    "em_loss_std": 8.981206431516718,
    "em_dead_mean": 24.4,
    "em_ttl_mean": 0,
    "delta_lat": 14.521664290901255,
    "losses_saved": 33.699999999999996
  },
  {
    "topology": "GEANT",
    "nodes": 40,
    "edges": 61,
    "density": 0.0782051282051282,
    "sp_lpp_mean": 10.169523333333334,
    "sp_lpp_std": 0.6820643496203188,
    "sp_loss_mean": 29.333333333333332,
    "sp_loss_std": 14.098993197934465,
    "em_lpp_mean": 10.562563333333333,
    "em_lpp_std": 0.7400757032494918,
    "em_loss_mean": 4.033333333333333,
    "em_loss_std": 2.326508903520663,
    "em_dead_mean": 4.066666666666666,
    "em_ttl_mean": 0,
    "delta_lat": 3.8648812448436534,
    "losses_saved": 25.299999999999997
  }
]